dictop.py
dictop-0.2.3.dist-info/licenses/LICENSE
dictop-0.2.3.dist-info/METADATA
dictop-0.2.3.dist-info/WHEEL
dictop-0.2.3.dist-info/top_level.txt
dictop-0.2.3.dist-info/RECORD
