Metadata-Version: 2.4
Name: dictop
Version: 0.2.3
Summary: DICT-OPERATION allow you select data value from a dict-instance with dot separated path, and update.
Author: rRR0VrFP
Maintainer: rRR0VrFP
License: MIT
Keywords: dictop
Classifier: Development Status :: 5 - Production/Stable
Classifier: Intended Audience :: Developers
Classifier: Topic :: Software Development :: Libraries :: Python Modules
Classifier: License :: OSI Approved :: MIT License
Classifier: Programming Language :: Python :: 3
Classifier: Programming Language :: Python :: 3 :: Only
License-File: LICENSE
Dynamic: author
Dynamic: classifier
Dynamic: description
Dynamic: description-content-type
Dynamic: keywords
Dynamic: license
Dynamic: license-file
Dynamic: maintainer
Dynamic: summary
